main.py
setup.py
laghtseq.egg-info/PKG-INFO
laghtseq.egg-info/SOURCES.txt
laghtseq.egg-info/dependency_links.txt
laghtseq.egg-info/requires.txt
laghtseq.egg-info/top_level.txt